ai_scaffold/__init__.py
ai_scaffold/__main__.py
ai_scaffold/generator.py
ai_scaffold/parser.py
ai_scaffold-1.0.0.dist-info/licenses/LICENSE
ai_scaffold-1.0.0.dist-info/METADATA
ai_scaffold-1.0.0.dist-info/WHEEL
ai_scaffold-1.0.0.dist-info/entry_points.txt
ai_scaffold-1.0.0.dist-info/top_level.txt
ai_scaffold-1.0.0.dist-info/RECORD
