Metadata-Version: 2.4
Name: ai-scaffold
Version: 1.0.0
Summary: Turn AI-generated Markdown or JSON into real project files
Author: Falah
License: MIT
Requires-Python: >=3.8
License-File: LICENSE
Dynamic: license-file
